firelink/__init__.py
firelink/_recipe_registry.py
firelink/recipe_interfaces.py
firelink/_cli/__init__.py
firelink/_cli/cp.py
firelink/_cli/download.py
firelink/_cli/ls.py
firelink/_cli/run.py
firelink/_cli/subcommand.py
firelink/_cli/tune.py
firelink/_cli/validate.py
firelink/config/__init__.py
firelink/config/_errors.py
firelink/config/_instantiate.py
firelink/config/_parse.py
firelink/config/_utils.py
firelink/config/_validate.py
firelink/data/__init__.py
firelink/data/_chat_formats.py
firelink/data/_common.py
firelink/data/_converters.py
firelink/data/_instruct_templates.py
firelink/data/_types.py
firelink/data/_utils.py
firelink/datasets/__init__.py
firelink/datasets/_alpaca.py
firelink/datasets/_chat.py
firelink/datasets/_cnn_dailymail.py
firelink/datasets/_concat.py
firelink/datasets/_grammar.py
firelink/datasets/_instruct.py
firelink/datasets/_packed.py
firelink/datasets/_preference.py
firelink/datasets/_samsum.py
firelink/datasets/_slimorca.py
firelink/datasets/_stack_exchanged_paired.py
firelink/datasets/_text_completion.py
firelink/datasets/_wikitext.py
firelink/models/__init__.py
firelink/models/convert_weights.py
firelink/models/clip/__init__.py
firelink/models/clip/_component_builders.py
firelink/models/clip/_model_builders.py
firelink/models/clip/_position_embeddings.py
firelink/models/clip/_transforms.py
firelink/models/code_llama2/__init__.py
firelink/models/code_llama2/_model_builders.py
firelink/models/gemma/__init__.py
firelink/models/gemma/_component_builders.py
firelink/models/gemma/_model_builders.py
firelink/models/gemma/_tokenizer.py
firelink/models/gemma/rms_norm.py
firelink/models/gemma/transformer.py
firelink/models/llama2/__init__.py
firelink/models/llama2/_component_builders.py
firelink/models/llama2/_model_builders.py
firelink/models/llama2/_model_utils.py
firelink/models/llama2/_tokenizer.py
firelink/models/llama3/__init__.py
firelink/models/llama3/_component_builders.py
firelink/models/llama3/_model_builders.py
firelink_shrine-0.0.0.dist-info/LICENSE
firelink_shrine-0.0.0.dist-info/METADATA
firelink_shrine-0.0.0.dist-info/WHEEL
firelink_shrine-0.0.0.dist-info/entry_points.txt
firelink_shrine-0.0.0.dist-info/top_level.txt
firelink_shrine-0.0.0.dist-info/RECORD
