Metadata-Version: 2.1
Name: firelink-shrine
Version: 0.0.0
Summary: A library for reproducible model training
Author-email: Randy Ardywibowo <ardywibowo.randy@gmail.com>
License: MIT License
Project-URL: GitHub, https://github.com/ardywibowo/firelink
Project-URL: Issues, https://github.com/ardywibowo/firelink/issues
Keywords: pytorch,finetuning,reproducibility
Requires-Python: >=3.8
License-File: LICENSE
Requires-Dist: datasets
Requires-Dist: huggingface-hub
Requires-Dist: safetensors
Requires-Dist: sentencepiece
Requires-Dist: tiktoken
Requires-Dist: blobfile >=2
Requires-Dist: numpy <=1.26.4
Requires-Dist: tqdm
Requires-Dist: omegaconf
Requires-Dist: torchao
Provides-Extra: dev
Requires-Dist: bitsandbytes >=0.43.0 ; extra == 'dev'
Requires-Dist: pre-commit ; extra == 'dev'
Requires-Dist: pytest ==7.4.0 ; extra == 'dev'
Requires-Dist: pytest-cov ; extra == 'dev'
Requires-Dist: pytest-mock ; extra == 'dev'
Requires-Dist: pytest-integration ; extra == 'dev'
Requires-Dist: tensorboard ; extra == 'dev'
Requires-Dist: wandb ; extra == 'dev'
Requires-Dist: expecttest ; extra == 'dev'
